cupyturbo/__init__.py
cupyturbo/dns_main.py
cupyturbo/dns_simulator.py
cupyturbo/dns_wrapper.py
mannetroll_cupyturbo-0.1.4.dist-info/licenses/LICENSE
mannetroll_cupyturbo-0.1.4.dist-info/METADATA
mannetroll_cupyturbo-0.1.4.dist-info/WHEEL
mannetroll_cupyturbo-0.1.4.dist-info/entry_points.txt
mannetroll_cupyturbo-0.1.4.dist-info/top_level.txt
mannetroll_cupyturbo-0.1.4.dist-info/RECORD
