Metadata-Version: 2.4
Name: mannetroll-cupyturbo
Version: 0.1.4
Summary: 2D DNS turbulence simulator (NumPy + CuPy)
Author: Torbjörn Sjögren
License: MIT License
Requires-Python: <3.14,>=3.13
License-File: LICENSE
Requires-Dist: numpy>=2.0.0
Requires-Dist: pillow>=10.0
Requires-Dist: PyQt6>=6.7
Provides-Extra: gpu
Requires-Dist: cupy>=13.0; extra == "gpu"
Dynamic: license-file
